LICENSE
README.md
setup.py
python3_ssh.egg-info/PKG-INFO
python3_ssh.egg-info/SOURCES.txt
python3_ssh.egg-info/dependency_links.txt
python3_ssh.egg-info/requires.txt
python3_ssh.egg-info/top_level.txt
ssh/__init__.py
ssh/ssh.py